{
    "occurances": {
        "w": 5839,
        "i": 11870,
        "l": 3453,
        "a": 12103,
        "m": 5494,
        "s": 6026,
        "h": 2111,
        "k": 4305,
        "e": 11736,
        "p": 3721,
        "r": 6131,
        "t": 5871,
        "\u00f3": 1528,
        "c": 5999,
        "z": 8425,
        "d": 4614,
        "u": 2796,
        "\u0144": 238,
        "\u0142": 2562,
        "j": 3667,
        "f": 269,
        "o": 10647,
        "b": 2590,
        "n": 7038,
        "7": 3,
        "8": 10,
        "3": 4,
        "2": 7,
        "6": 2,
        "y": 5318,
        "g": 2211,
        "\u017a": 210,
        "\u0105": 1681,
        "\u017c": 1672,
        "\u0119": 2222,
        "\u015b": 1464,
        "\u0107": 1084,
        "q": 2,
        "1": 4
    },
    "percent_occurances": {
        "w": 4.03,
        "i": 8.19,
        "l": 2.38,
        "a": 8.35,
        "m": 3.79,
        "s": 4.16,
        "h": 1.46,
        "k": 2.97,
        "e": 8.1,
        "p": 2.57,
        "r": 4.23,
        "t": 4.05,
        "\u00f3": 1.05,
        "c": 4.14,
        "z": 5.81,
        "d": 3.18,
        "u": 1.93,
        "\u0144": 0.16,
        "\u0142": 1.77,
        "j": 2.53,
        "f": 0.19,
        "o": 7.35,
        "b": 1.79,
        "n": 4.86,
        "7": 0.0,
        "8": 0.01,
        "3": 0.0,
        "2": 0.0,
        "6": 0.0,
        "y": 3.67,
        "g": 1.53,
        "\u017a": 0.14,
        "\u0105": 1.16,
        "\u017c": 1.15,
        "\u0119": 1.53,
        "\u015b": 1.01,
        "\u0107": 0.75,
        "q": 0.0,
        "1": 0.0
    },
    "most_common_letter": [
        [
            "a",
            12103
        ],
        8.35
    ],
    "total_letters": 144927,
    "vowels": [
        59901,
        41.33
    ],
    "consonants": [
        85026,
        58.67
    ],
    "longest_words": [
        2,
        [
            "najzbawienniejszymi",
            "prawdopodobie\u0144stwem"
        ]
    ]
}